DatastreamPy/DSConnect.py
DatastreamPy/DSUserDataObjectBase.py
DatastreamPy/DS_Requests.py
DatastreamPy/DS_Response.py
DatastreamPy/DatastreamEconomicFilters.py
DatastreamPy/DatastreamUserCreated_TimeSeries.py
DatastreamPy/__init__.py
DatastreamPy-2.0.30.dist-info/METADATA
DatastreamPy-2.0.30.dist-info/WHEEL
DatastreamPy-2.0.30.dist-info/top_level.txt
DatastreamPy-2.0.30.dist-info/RECORD
