Metadata-Version: 2.1
Name: DatastreamPy
Version: 2.0.30
Summary: Python package for Datastream Web Services API
Author: LSEG
Author-email: datastreamapi@lseg.com
License: Apache Software License (http://www.apache.org/licenses/LICENSE-2.0)
Requires-Python: >=3
Requires-Dist: pandas
Requires-Dist: requests
